{"cameraMode":{"drawMode":0,"name":"Shaded","section":"Shading Mode"},"sceneLighting":true,"audioPlay":false,"sceneViewState":{"showFog":true,"showMaterialUpdate":false,"showSkybox":true,"showFlares":true,"showImageEffects":true,"showParticleSystems":true},"in2DMode":false,"pivot":{"x":67.00979614257813,"y":3.8308353424072267,"z":40.29302978515625},"rotation":{"x":0.04344581440091133,"y":-0.9490104913711548,"z":0.15071022510528565,"w":0.2734556496143341},"size":37.48231887817383,"orthographic":false}